rich_form/__init__.py
rich_form/__main__.py
rich_form/base/__init__.py
rich_form/base/abstract.py
rich_form/base/exc.py
rich_form/base/styles.py
rich_form/base/utils.py
rich_form/field.py
rich_form/mixins.py
rich_form/render.py
rich_form/visualize.py
rich_form-0.1.1.dist-info/METADATA
rich_form-0.1.1.dist-info/WHEEL
rich_form-0.1.1.dist-info/RECORD
